{
	"TrackName": "acu_hungaroring",
	"TrackConfig": "",
	"Type": "QUALIFY",
	"DurationSecs": 0,
	"RaceLaps": 0,
	"Cars": [
		{
			"CarId": 0,
			"Driver": {
				"Name": "FABIO",
				"Team": "",
				"Nation": "AC",
				"Guid": "76561199437441668",
				"GuidsList": [
					""
				]
			},
			"Model": "tatuusfa1",
			"Skin": "scheme_0",
			"BallastKG": 0,
			"Restrictor": 0
		},
		{
			"CarId": 1,
			"Driver": {
				"Name": "CHRIS",
				"Team": "",
				"Nation": "AC",
				"Guid": "76561199482152288",
				"GuidsList": [
					""
				]
			},
			"Model": "tatuusfa1",
			"Skin": "scheme_1",
			"BallastKG": 0,
			"Restrictor": 0
		},
		{
			"CarId": 2,
			"Driver": {
				"Name": "",
				"Team": "",
				"Nation": "",
				"Guid": "",
				"GuidsList": [
					""
				]
			},
			"Model": "tatuusfa1",
			"Skin": "scheme_2",
			"BallastKG": 0,
			"Restrictor": 0
		},
		{
			"CarId": 3,
			"Driver": {
				"Name": "",
				"Team": "",
				"Nation": "",
				"Guid": "",
				"GuidsList": [
					""
				]
			},
			"Model": "tatuusfa1",
			"Skin": "scheme_3",
			"BallastKG": 0,
			"Restrictor": 0
		},
		{
			"CarId": 4,
			"Driver": {
				"Name": "",
				"Team": "",
				"Nation": "",
				"Guid": "",
				"GuidsList": [
					""
				]
			},
			"Model": "tatuusfa1",
			"Skin": "scheme_4",
			"BallastKG": 0,
			"Restrictor": 0
		}
	],
	"Result": [
		{
			"DriverName": "FABIO",
			"DriverGuid": "76561199437441668",
			"CarId": 0,
			"CarModel": "tatuusfa1",
			"BestLap": 110738,
			"TotalTime": 350486,
			"BallastKG": 0,
			"Restrictor": 0
		},
		{
			"DriverName": "CHRIS",
			"DriverGuid": "76561199482152288",
			"CarId": 1,
			"CarModel": "tatuusfa1",
			"BestLap": 119096,
			"TotalTime": 443660,
			"BallastKG": 0,
			"Restrictor": 0
		},
		{
			"DriverName": "",
			"DriverGuid": "",
			"CarId": 2,
			"CarModel": "tatuusfa1",
			"BestLap": 999999999,
			"TotalTime": 0,
			"BallastKG": 0,
			"Restrictor": 0
		},
		{
			"DriverName": "",
			"DriverGuid": "",
			"CarId": 3,
			"CarModel": "tatuusfa1",
			"BestLap": 999999999,
			"TotalTime": 0,
			"BallastKG": 0,
			"Restrictor": 0
		},
		{
			"DriverName": "",
			"DriverGuid": "",
			"CarId": 4,
			"CarModel": "tatuusfa1",
			"BestLap": 999999999,
			"TotalTime": 0,
			"BallastKG": 0,
			"Restrictor": 0
		}
	],
	"Laps": [
		{
			"DriverName": "FABIO",
			"DriverGuid": "76561199437441668",
			"CarId": 0,
			"CarModel": "tatuusfa1",
			"Timestamp": 5404735,
			"LapTime": 128545,
			"Sectors": [
				56973,
				40927,
				30645
			],
			"Cuts": 0,
			"BallastKG": 0,
			"Tyre": "M",
			"Restrictor": 0
		},
		{
			"DriverName": "CHRIS",
			"DriverGuid": "76561199482152288",
			"CarId": 1,
			"CarModel": "tatuusfa1",
			"Timestamp": 5477916,
			"LapTime": 155039,
			"Sectors": [
				70291,
				51575,
				33173
			],
			"Cuts": 0,
			"BallastKG": 0,
			"Tyre": "M",
			"Restrictor": 0
		},
		{
			"DriverName": "FABIO",
			"DriverGuid": "76561199437441668",
			"CarId": 0,
			"CarModel": "tatuusfa1",
			"Timestamp": 5515966,
			"LapTime": 111209,
			"Sectors": [
				41081,
				39470,
				30658
			],
			"Cuts": 0,
			"BallastKG": 0,
			"Tyre": "M",
			"Restrictor": 0
		},
		{
			"DriverName": "CHRIS",
			"DriverGuid": "76561199482152288",
			"CarId": 1,
			"CarModel": "tatuusfa1",
			"Timestamp": 5600726,
			"LapTime": 122808,
			"Sectors": [
				43342,
				46917,
				32549
			],
			"Cuts": 0,
			"BallastKG": 0,
			"Tyre": "M",
			"Restrictor": 0
		},
		{
			"DriverName": "FABIO",
			"DriverGuid": "76561199437441668",
			"CarId": 0,
			"CarModel": "tatuusfa1",
			"Timestamp": 5626670,
			"LapTime": 110738,
			"Sectors": [
				41119,
				38808,
				30811
			],
			"Cuts": 0,
			"BallastKG": 0,
			"Tyre": "M",
			"Restrictor": 0
		},
		{
			"DriverName": "CHRIS",
			"DriverGuid": "76561199482152288",
			"CarId": 1,
			"CarModel": "tatuusfa1",
			"Timestamp": 5719820,
			"LapTime": 119096,
			"Sectors": [
				43073,
				44524,
				31499
			],
			"Cuts": 0,
			"BallastKG": 0,
			"Tyre": "M",
			"Restrictor": 0
		}
	],
	"Events": null
}